{
	"name": "pipeline1",
	"properties": {
		"activities": [
			{
				"name": "df_Demo",
				"type": "ExecuteDataFlow",
				"dependsOn": [],
				"policy": {
					"timeout": "1.00:00:00",
					"retry": 0,
					"retryIntervalInSeconds": 30,
					"secureOutput": false,
					"secureInput": false
				},
				"userProperties": [],
				"typeProperties": {
					"dataflow": {
						"referenceName": "df_Demo",
						"type": "DataFlowReference"
					},
					"compute": {
						"coreCount": 8,
						"computeType": "General"
					},
					"traceLevel": "Fine"
				}
			},
			{
				"name": "Procedure",
				"type": "SqlServerStoredProcedure",
				"dependsOn": [
					{
						"activity": "df_Demo",
						"dependencyConditions": [
							"Succeeded"
						]
					}
				],
				"policy": {
					"timeout": "7.00:00:00",
					"retry": 0,
					"retryIntervalInSeconds": 30,
					"secureOutput": false,
					"secureInput": false
				},
				"userProperties": [],
				"typeProperties": {
					"storedProcedureName": "[dbo].[usp_ProcessIPBills]"
				},
				"linkedServiceName": {
					"referenceName": "ls_AzureSQLDB",
					"type": "LinkedServiceReference"
				}
			}
		],
		"annotations": []
	}
}